conch/downstream/__init__.py
conch/downstream/tile_datasets.py
conch/downstream/utils.py
conch/downstream/wsi_datasets.py
conch/downstream/zeroshot_path.py
conch/open_clip_custom/__init__.py
conch/open_clip_custom/coca_model.py
conch/open_clip_custom/constants.py
conch/open_clip_custom/custom_tokenizer.py
conch/open_clip_custom/factory.py
conch/open_clip_custom/transform.py
conch/open_clip_custom/transformer.py
conch/open_clip_custom/utils.py
conch/open_clip_custom/vision_tower.py
conch/open_clip_custom/model_configs/conch_ViT-B-16.json
conch/open_clip_custom/tokenizers/conch_byte_level_bpe_uncased.json
conch_fork-0.1.0.dist-info/LICENSE
conch_fork-0.1.0.dist-info/METADATA
conch_fork-0.1.0.dist-info/WHEEL
conch_fork-0.1.0.dist-info/top_level.txt
conch_fork-0.1.0.dist-info/RECORD
