Metadata-Version: 2.1
Name: conch-fork
Version: 0.1.0
Summary: CONCH: a vision language foundation model for human pathology.
License: # Attribution-NonCommercial-NoDerivatives 4.0 International
Classifier: Programming Language :: Python :: 3
Requires-Python: >=3.9
License-File: LICENSE
Requires-Dist: torch >=2.0.1
Requires-Dist: torchvision
Requires-Dist: transformers
Requires-Dist: tokenizers
Requires-Dist: numpy
Requires-Dist: scikit-learn
Requires-Dist: timm >=0.9.8
Requires-Dist: regex
Requires-Dist: ftfy
Requires-Dist: h5py
Requires-Dist: pandas
